stats_compass_core/__init__.py
stats_compass_core/base.py
stats_compass_core/cleaning/__init__.py
stats_compass_core/cleaning/apply_imputation.py
stats_compass_core/cleaning/clean_dates.py
stats_compass_core/cleaning/dedupe.py
stats_compass_core/cleaning/dropna.py
stats_compass_core/cleaning/handle_outliers.py
stats_compass_core/data/__init__.py
stats_compass_core/data/add_column.py
stats_compass_core/data/concat_dataframes.py
stats_compass_core/data/drop_columns.py
stats_compass_core/data/get_sample.py
stats_compass_core/data/get_schema.py
stats_compass_core/data/inspect_data.py
stats_compass_core/data/list_dataframes.py
stats_compass_core/data/list_files.py
stats_compass_core/data/load_csv.py
stats_compass_core/data/load_dataset.py
stats_compass_core/data/load_excel.py
stats_compass_core/data/merge_dataframes.py
stats_compass_core/data/rename_columns.py
stats_compass_core/data/save_csv.py
stats_compass_core/datasets/Bukayo_Saka_7322.csv
stats_compass_core/datasets/Housing.csv
stats_compass_core/datasets/TATASTEEL.csv
stats_compass_core/eda/__init__.py
stats_compass_core/eda/chi_square_tests.py
stats_compass_core/eda/correlations.py
stats_compass_core/eda/data_quality.py
stats_compass_core/eda/describe.py
stats_compass_core/eda/hypothesis_tests.py
stats_compass_core/ml/__init__.py
stats_compass_core/ml/common.py
stats_compass_core/ml/save_model.py
stats_compass_core/ml/supervised/__init__.py
stats_compass_core/ml/supervised/evaluate_classification_model.py
stats_compass_core/ml/supervised/evaluate_regression_model.py
stats_compass_core/ml/supervised/train_gradient_boosting_classifier.py
stats_compass_core/ml/supervised/train_gradient_boosting_regressor.py
stats_compass_core/ml/supervised/train_linear_regression.py
stats_compass_core/ml/supervised/train_logistic_regression.py
stats_compass_core/ml/supervised/train_random_forest_classifier.py
stats_compass_core/ml/supervised/train_random_forest_regressor.py
stats_compass_core/ml/timeseries/__init__.py
stats_compass_core-0.1.15.dist-info/LICENSE
stats_compass_core-0.1.15.dist-info/METADATA
stats_compass_core-0.1.15.dist-info/WHEEL
stats_compass_core-0.1.15.dist-info/RECORD
