Metadata-Version: 2.3
Name: stats-compass-core
Version: 0.1.15
Summary: A clean toolkit of deterministic pandas-based data tools
License: MIT
Keywords: pandas,data,tools,data-science,eda,ml
Author: Olatunji Ogunbiyi
Author-email: oogunbiyi21@users.noreply.github.com
Requires-Python: >=3.11,<4.0
Classifier: Development Status :: 3 - Alpha
Classifier: Intended Audience :: Developers
Classifier: Intended Audience :: Science/Research
Classifier: License :: OSI Approved :: MIT License
Classifier: Programming Language :: Python :: 3
Classifier: Programming Language :: Python :: 3.11
Classifier: Programming Language :: Python :: 3.12
Classifier: Programming Language :: Python :: 3.13
Classifier: Topic :: Scientific/Engineering
Classifier: Topic :: Software Development :: Libraries :: Python Modules
Provides-Extra: all
Provides-Extra: excel
Provides-Extra: ml
Provides-Extra: parquet
Provides-Extra: plots
Provides-Extra: timeseries
Requires-Dist: joblib (>=1.5.2,<2.0.0)
Requires-Dist: matplotlib (>=3.6.0,<4.0.0) ; extra == "plots" or extra == "timeseries" or extra == "all"
Requires-Dist: numpy (>=2.0.0,<3.0.0)
Requires-Dist: openpyxl (>=3.1.0,<4.0.0) ; extra == "excel" or extra == "all"
Requires-Dist: pandas (>=2.0.0,<3.0.0)
Requires-Dist: pyarrow (>=18.0.0,<19.0.0) ; extra == "parquet" or extra == "all"
Requires-Dist: pydantic (>=2.0.0,<3.0.0)
Requires-Dist: scikit-learn (>=1.3.0,<2.0.0) ; extra == "ml" or extra == "all"
Requires-Dist: scipy (>=1.13.0,<2.0.0)
Requires-Dist: seaborn (>=0.12.0,<0.13.0) ; extra == "plots" or extra == "all"
Requires-Dist: statsmodels (>=0.14.0,<0.15.0) ; extra == "timeseries" or extra == "all"
